archetypal-stubs/__init__.pyi
archetypal-stubs/idfclass/__init__.pyi
archetypal-stubs/idfclass/idf.pyi
archetypal-stubs/py.typed
archetypal_stubs-0.1.6.dist-info/WHEEL
archetypal_stubs-0.1.6.dist-info/METADATA
archetypal_stubs-0.1.6.dist-info/RECORD
