Metadata-Version: 2.3
Name: archetypal-stubs
Version: 0.1.6
Summary: Eppy type stubs for the archetypal package
Keywords: archetypal,typing,stubs
Author: Samuel Letellier-Duchesne
Author-email: Samuel Letellier-Duchesne <samuelduchesne@me.com>
Classifier: Typing :: Stubs Only
Classifier: Programming Language :: Python :: 3
Requires-Dist: types-eplus2310 ; extra == 'eplus2310'
Requires-Python: >=3.9, <4.0
Provides-Extra: eplus2310
